serp_onpremise/__init__.py
serp_onpremise/asm/__init__.py
serp_onpremise/asm/v1.py
serp_onpremise/auth/__init__.py
serp_onpremise/auth/v1.py
serp_onpremise/auth_token.py
serp_onpremise/base.py
serp_onpremise/clients.py
serp_onpremise/compare/__init__.py
serp_onpremise/compare/v1.py
serp_onpremise/constants.py
serp_onpremise/entries/__init__.py
serp_onpremise/entries/v1.py
serp_onpremise/groups_profiles/__init__.py
serp_onpremise/groups_profiles/v1.py
serp_onpremise/licenses/__init__.py
serp_onpremise/licenses/v1.py
serp_onpremise/liveness/__init__.py
serp_onpremise/liveness/v1.py
serp_onpremise/origins/__init__.py
serp_onpremise/origins/v1.py
serp_onpremise/profiles/__init__.py
serp_onpremise/profiles/v1.py
serp_onpremise/spaces/__init__.py
serp_onpremise/spaces/v1.py
serp_onpremise/statistics/__init__.py
serp_onpremise/statistics/v1.py
serp_onpremise/tokens/__init__.py
serp_onpremise/tokens/access/__init__.py
serp_onpremise/tokens/access/v1.py
serp_onpremise/tokens/streams/__init__.py
serp_onpremise/tokens/streams/v1.py
serp_onpremise/users/__init__.py
serp_onpremise/users/v1.py
serp_onpremise/utils.py
serp_onpremise/whoami/__init__.py
serp_onpremise/whoami/v1.py
serp_onpremise-0.1.2.dist-info/LICENSE
serp_onpremise-0.1.2.dist-info/WHEEL
serp_onpremise-0.1.2.dist-info/METADATA
serp_onpremise-0.1.2.dist-info/RECORD
