Metadata-Version: 2.1
Name: serp-onpremise
Version: 0.1.2
Summary: A Python package for interacting with SERP on-premise API
License: MIT
Author: serptech.ru
Requires-Python: >=3.8.0,<4.0.0
Classifier: License :: OSI Approved :: MIT License
Classifier: Programming Language :: Python :: 3
Classifier: Programming Language :: Python :: 3.8
Classifier: Programming Language :: Python :: 3.9
Classifier: Programming Language :: Python :: 3.10
Classifier: Programming Language :: Python :: 3.11
Requires-Dist: httpx (>=0.19.0)
Requires-Dist: sphinx (>=7.0.1,<8.0.0)
Requires-Dist: websockets (>=10.0,<11.0)
